exceltopostgresql/__init__.py
exceltopostgresql/_model.py
exceltopostgresql/exceltopostgresql.py
exceltopostgresql-0.2.4.dist-info/LICENSE
exceltopostgresql-0.2.4.dist-info/METADATA
exceltopostgresql-0.2.4.dist-info/WHEEL
exceltopostgresql-0.2.4.dist-info/top_level.txt
exceltopostgresql-0.2.4.dist-info/RECORD
